sugus_mcp_demo/__init__.py
sugus_mcp_demo-0.1.0.dist-info/WHEEL
sugus_mcp_demo-0.1.0.dist-info/entry_points.txt
sugus_mcp_demo-0.1.0.dist-info/METADATA
sugus_mcp_demo-0.1.0.dist-info/RECORD
