Metadata-Version: 2.3
Name: sugus-mcp-demo
Version: 0.1.0
Summary: Add your description here
Author: Billy
Author-email: Billy <57972928@qq.com>
Requires-Dist: mcp[cli]>=1.13.1
Requires-Python: >=3.11
